code_genie/__init__.py
code_genie/_cache.py
code_genie/client.py
code_genie/genie.py
code_genie-0.3.1.dist-info/LICENSE
code_genie-0.3.1.dist-info/WHEEL
code_genie-0.3.1.dist-info/METADATA
code_genie-0.3.1.dist-info/RECORD
